fpyo2apk/__init__.py
fpyo2apk/build.py
fpyo2apk/Tools/__init__.py
fpyo2apk/Tools/check_system.py
fpyo2apk/Tools/check_venv.py
fpyo2apk/Tools/unzip_assets.py
fpyo2apk/assets/__init__.py
fpyo2apk/assets/fpyo2apkdist.zip
fpyo2apk/beeware_tools/__init__.py
fpyo2apk/beeware_tools/edit_beeware_project.py
fpyo2apk/beeware_tools/the_app_py.py
fpyo2apk/beeware_tools/the_localhost_py.py
fpyo2apk-1.1.4.dist-info/LICENSE
fpyo2apk-1.1.4.dist-info/METADATA
fpyo2apk-1.1.4.dist-info/WHEEL
fpyo2apk-1.1.4.dist-info/top_level.txt
fpyo2apk-1.1.4.dist-info/RECORD
