Metadata-Version: 2.1
Name: fpyo2apk
Version: 1.1.4
Summary: A package tool that allow you to built a python Android apps with flet-pyodide dist.
Home-page: https://github.com/SKbarbon/fpyo2apk
Author: SKbarbon
Classifier: Programming Language :: Python :: 3
Classifier: Operating System :: MacOS :: MacOS X
Classifier: Operating System :: Microsoft :: Windows
License-File: LICENSE
Requires-Dist: briefcase (==0.3.14)
